gogettr/__init__.py
gogettr/api.py
gogettr/capabilities/__init__.py
gogettr/capabilities/all.py
gogettr/capabilities/base.py
gogettr/capabilities/comments.py
gogettr/capabilities/hashtags.py
gogettr/capabilities/live.py
gogettr/capabilities/search.py
gogettr/capabilities/suggested.py
gogettr/capabilities/trends.py
gogettr/capabilities/user_activity.py
gogettr/capabilities/user_info.py
gogettr/capabilities/user_relationships.py
gogettr/cli.py
gogettr/errors.py
gogettr/public.py
gogettr/utils.py
gogettr-0.9.0.dist-info/LICENSE
gogettr-0.9.0.dist-info/METADATA
gogettr-0.9.0.dist-info/WHEEL
gogettr-0.9.0.dist-info/entry_points.txt
gogettr-0.9.0.dist-info/RECORD
