Metadata-Version: 2.1
Name: gogettr
Version: 0.9.0
Summary: Extraction tool for GETTR, a "non-bias [sic] social network."
Home-page: https://github.com/stanfordio/gogettr
License: Apache-2.0
Keywords: gettr,scraper,cli
Author: Stanford Internet Observatory
Author-email: mccain@stanford.edu
Requires-Python: >=3.8,<4.0
Classifier: License :: OSI Approved :: Apache Software License
Classifier: Programming Language :: Python :: 3
Classifier: Programming Language :: Python :: 3.8
Classifier: Programming Language :: Python :: 3.9
Classifier: Programming Language :: Python :: 3.10
Classifier: Programming Language :: Python :: 3.11
Requires-Dist: click (>=8.0.1,<9.0.0)
Requires-Dist: requests (>=2.25.1,<3.0.0)
